rsclib/Config_File.py
rsclib/IP_Address.py
rsclib/Math.py
rsclib/PDF_Signature.py
rsclib/PM_Value.py
rsclib/Phone.py
rsclib/TeX_CSV_Writer.py
rsclib/Version.py
rsclib/__init__.py
rsclib/ast_call.py
rsclib/ast_cdr.py
rsclib/ast_probe.py
rsclib/autosuper.py
rsclib/base_pickler.py
rsclib/bero.py
rsclib/capacitance.py
rsclib/crm.py
rsclib/execute.py
rsclib/grepmime.py
rsclib/hexdump.py
rsclib/inductance.py
rsclib/isdn.py
rsclib/iter_recipes.py
rsclib/lc_resonator.py
rsclib/nmap.py
rsclib/ocf.py
rsclib/pycompat.py
rsclib/rational.py
rsclib/sqlparser.py
rsclib/stateparser.py
rsclib/timeout.py
rsclib/trafficshape.py
rsclib-0.68.dist-info/licenses/LICENSE
rsclib-0.68.dist-info/METADATA
rsclib-0.68.dist-info/WHEEL
rsclib-0.68.dist-info/entry_points.txt
rsclib-0.68.dist-info/top_level.txt
rsclib-0.68.dist-info/RECORD
