Metadata-Version: 2.4
Name: rsclib
Version: 0.68
Summary: Misc. basic stuff needed by RSCs tools
Home-page: http://rsclib.sourceforge.net/
Download-URL: http://downloads.sourceforge.net/project/rsclib/rsclib/0.68/rsclib-0.68.tar.gz
Author: Ralf Schlatterbeck
Author-email: Ralf Schlatterbeck <rsc@runtux.com>
License-Expression: MIT
Project-URL: Homepage, https://github.com/schlatterbeck/rsclib
Project-URL: Bug Tracker, https://github.com/schlatterbeck/rsclib/issues
Platform: Any
Classifier: Development Status :: 5 - Production/Stable
Classifier: Operating System :: OS Independent
Classifier: Programming Language :: Python
Classifier: Intended Audience :: Developers
Classifier: Programming Language :: Python :: 2
Classifier: Programming Language :: Python :: 2.7
Classifier: Programming Language :: Python :: 3
Classifier: Programming Language :: Python :: 3.5
Classifier: Programming Language :: Python :: 3.6
Classifier: Programming Language :: Python :: 3.7
Classifier: Programming Language :: Python :: 3.8
Classifier: Programming Language :: Python :: 3.9
Classifier: Programming Language :: Python :: 3.10
Classifier: Programming Language :: Python :: 3.11
Requires-Python: >=2.7, !=3.0.*, !=3.1.*, !=3.2.*, !=3.3.*, !=3.4.*, <4
License-File: LICENSE
Dynamic: author
Dynamic: download-url
Dynamic: home-page
Dynamic: license-file
Dynamic: platform
Dynamic: requires-python
